mlcvzoo_yolox/__init__.py
mlcvzoo_yolox/configuration.py
mlcvzoo_yolox/model.py
mlcvzoo_yolox/model_utils.py
mlcvzoo_yolox/py.typed
mlcvzoo_yolox/core/__init__.py
mlcvzoo_yolox/core/trainer.py
mlcvzoo_yolox/data/__init__.py
mlcvzoo_yolox/data/datasets/__init__.py
mlcvzoo_yolox/data/datasets/dataset.py
mlcvzoo_yolox/evaluators/__init__.py
mlcvzoo_yolox/evaluators/evaluator.py
mlcvzoo_yolox/exp/__init__.py
mlcvzoo_yolox/exp/custom_yolox_exp.py
mlcvzoo_yolox/exp/default.py
mlcvzoo_yolox/third_party/__init__.py
mlcvzoo_yolox/third_party/yolox/__init__.py
mlcvzoo_yolox/third_party/yolox/exps/__init__.py
mlcvzoo_yolox/third_party/yolox/exps/yolox_base.py
mlcvzoo_yolox/third_party/yolox/exps/yolox_nano.py
mlcvzoo_yolox/third_party/yolox/models/__init__.py
mlcvzoo_yolox/third_party/yolox/models/yolo_head.py
mlcvzoo_yolox/third_party/yolox/tools/__init__.py
mlcvzoo_yolox/third_party/yolox/tools/train.py
mlcvzoo_yolox/third_party/yolox/tools/trt.py
mlcvzoo_yolox/third_party/yolox/utils/__init__.py
mlcvzoo_yolox/third_party/yolox/utils/boxes.py
mlcvzoo_yolox-6.2.1.dist-info/LICENSE
mlcvzoo_yolox-6.2.1.dist-info/METADATA
mlcvzoo_yolox-6.2.1.dist-info/WHEEL
mlcvzoo_yolox-6.2.1.dist-info/top_level.txt
mlcvzoo_yolox-6.2.1.dist-info/RECORD
